SoSciKit-0.4.0.dist-info/DESCRIPTION.rst
SoSciKit-0.4.0.dist-info/METADATA
SoSciKit-0.4.0.dist-info/RECORD
SoSciKit-0.4.0.dist-info/WHEEL
SoSciKit-0.4.0.dist-info/metadata.json
SoSciKit-0.4.0.dist-info/top_level.txt
soscikit/__init__.py
soscikit/__main__.py
soscikit/description.py
soscikit/elab.py
soscikit/run.py
soscikit/plotting/__init__.py
soscikit/plotting/altarian.py
soscikit/plotting/matplotting.py
soscikit/plotting/__pycache__/__init__.cpython-36.pyc
soscikit/plotting/__pycache__/__init__.cpython-37.pyc
soscikit/plotting/__pycache__/altarian.cpython-36.pyc
soscikit/plotting/__pycache__/altarian.cpython-37.pyc
soscikit/static/css/bootstrap.min.css
soscikit/static/css/dragtable.js
soscikit/static/css/jquery.dataTables.min.css
soscikit/static/images/1page.jpg
soscikit/static/images/analysis.svg
soscikit/static/images/database.svg
soscikit/static/images/programming.svg
soscikit/static/images/statistics.svg
soscikit/static/js/bootstrap.min.js
soscikit/static/js/jquery-3.4.1.min.js
soscikit/static/js/jquery.dataTables.min.js
soscikit/static/js/popper.min.js
soscikit/static/uploads/Unosostenibile.xlsx
soscikit/static/uploads/titanic.xlsx
soscikit/stats_tools/__init__.py
soscikit/stats_tools/table.py
soscikit/stats_tools/tools.py
soscikit/stats_tools/__pycache__/__init__.cpython-36.pyc
soscikit/stats_tools/__pycache__/__init__.cpython-37.pyc
soscikit/stats_tools/__pycache__/table.cpython-36.pyc
soscikit/stats_tools/__pycache__/table.cpython-37.pyc
soscikit/stats_tools/__pycache__/tools.cpython-36.pyc
soscikit/stats_tools/__pycache__/tools.cpython-37.pyc
soscikit/templates/calc.html
soscikit/templates/calc_output.html
soscikit/templates/create_subset.html
soscikit/templates/guide.html
soscikit/templates/index.html
soscikit/templates/layout.html
soscikit/templates/profiling.html
soscikit/templates/select_action.html
soscikit/templates/bivariate/bivariate_plot.html
soscikit/templates/bivariate/bivariate_selection.html
soscikit/templates/cluster/cluster_output.html
soscikit/templates/cluster/cluster_selection.html
soscikit/templates/crosstab/crosstab_classification.html
soscikit/templates/crosstab/crosstab_classification_output.html
